mindoc.py
mindoc-0.5.0.dist-info/LICENSE
mindoc-0.5.0.dist-info/METADATA
mindoc-0.5.0.dist-info/WHEEL
mindoc-0.5.0.dist-info/entry_points.txt
mindoc-0.5.0.dist-info/top_level.txt
mindoc-0.5.0.dist-info/RECORD
