Metadata-Version: 2.1
Name: mindoc
Version: 0.5.0
Summary: A minimalistic python documentation tool.
Home-page: https://minchulkim87.github.io/mindoc/
Author: Min Chul Kim
Author-email: minchulkim87@gmail.com
License: UNKNOWN
Platform: UNKNOWN
Classifier: Programming Language :: Python :: 3
Classifier: License :: OSI Approved :: MIT License
Classifier: Operating System :: OS Independent
Requires-Python: >=3.6
Requires-Dist: appdirs (==1.4.4)
Requires-Dist: attrs (==19.3.0)
Requires-Dist: beautifulsoup4 (==4.9.1)
Requires-Dist: cached-property (==1.5.1)
Requires-Dist: cerberus (==1.3.2)
Requires-Dist: certifi (==2020.4.5.1)
Requires-Dist: chardet (==3.0.4)
Requires-Dist: click (==7.1.2)
Requires-Dist: colorama (==0.4.3)
Requires-Dist: distlib (==0.3.0)
Requires-Dist: idna (==2.9)
Requires-Dist: mistune (==0.8.4)
Requires-Dist: orderedmultidict (==1.0.1)
Requires-Dist: packaging (==19.2)
Requires-Dist: pathspec (==0.8.0)
Requires-Dist: pep517 (==0.8.2)
Requires-Dist: pip-shims (==0.5.2)
Requires-Dist: pipenv-setup (==3.0.1)
Requires-Dist: pipfile (==0.0.2)
Requires-Dist: plette[validation] (==0.2.3)
Requires-Dist: pyparsing (==2.4.7)
Requires-Dist: python-dateutil (==2.8.1)
Requires-Dist: regex (==2020.5.14)
Requires-Dist: requests (==2.23.0)
Requires-Dist: requirementslib (==1.5.9)
Requires-Dist: six (==1.15.0)
Requires-Dist: soupsieve (==2.0.1)
Requires-Dist: toml (==0.10.1)
Requires-Dist: tomlkit (==0.6.0)
Requires-Dist: typed-ast (==1.4.1)
Requires-Dist: typing (==3.7.4.1)
Requires-Dist: urllib3 (==1.25.9)
Requires-Dist: vistir (==0.5.2)
Requires-Dist: wheel (==0.34.2)
Requires-Dist: black (==19.10b0) ; python_version >= "3.6"
